dbbasic_content/__init__.py
dbbasic_content/blocks.py
dbbasic_content/cli.py
dbbasic_content/content.py
dbbasic_content/wordpress_importer.py
dbbasic_content-0.2.0.dist-info/licenses/LICENSE
dbbasic_content-0.2.0.dist-info/METADATA
dbbasic_content-0.2.0.dist-info/WHEEL
dbbasic_content-0.2.0.dist-info/entry_points.txt
dbbasic_content-0.2.0.dist-info/top_level.txt
dbbasic_content-0.2.0.dist-info/RECORD
