Metadata-Version: 2.4
Name: dbbasic-content
Version: 0.2.0
Summary: Unix-foundation content management for web apps - WordPress escape toolkit
Home-page: https://github.com/askrobots/dbbasic-content
Author: Dan Quellhorst
Author-email: Dan Quellhorst <dan@quellhorst.com>
License: MIT
Project-URL: Homepage, https://github.com/askrobots/dbbasic-content
Project-URL: Documentation, https://github.com/askrobots/dbbasic-content#readme
Project-URL: Repository, https://github.com/askrobots/dbbasic-content
Project-URL: Bug Tracker, https://github.com/askrobots/dbbasic-content/issues
Keywords: cms,content-management,wordpress,unix,blocks,json
Classifier: Development Status :: 3 - Alpha
Classifier: Intended Audience :: Developers
Classifier: Topic :: Software Development :: Libraries :: Python Modules
Classifier: License :: OSI Approved :: MIT License
Classifier: Programming Language :: Python :: 3
Classifier: Programming Language :: Python :: 3.8
Classifier: Programming Language :: Python :: 3.9
Classifier: Programming Language :: Python :: 3.10
Classifier: Programming Language :: Python :: 3.11
Requires-Python: >=3.8
License-File: LICENSE
Requires-Dist: dbbasic-tsv>=1.0.0
Provides-Extra: dev
Requires-Dist: pytest>=7.0; extra == "dev"
Requires-Dist: pytest-cov>=4.0; extra == "dev"
Provides-Extra: wordpress
Requires-Dist: pymysql>=1.0; extra == "wordpress"
Dynamic: author
Dynamic: home-page
Dynamic: license-file
Dynamic: requires-python
